araugment/__init__.py
araugment/augment.py
araugment-1.0.0.dist-info/LICENSE
araugment-1.0.0.dist-info/METADATA
araugment-1.0.0.dist-info/WHEEL
araugment-1.0.0.dist-info/top_level.txt
araugment-1.0.0.dist-info/RECORD
