Metadata-Version: 2.1
Name: araugment
Version: 1.0.0
Summary: Augment Arabic data for deep learning tasks
Home-page: https://github.com/ashaheedq/araugment
Author: Abdulshaheed Alqunber
Author-email: abdulshaheed.qunber@kaust.edu.sa
License: MIT
Project-URL: Documentation, https://github.com/ashaheedq/araugment
Project-URL: Bug Reports, https://github.com/ashaheedq/araugment/issues
Project-URL: Source Code, https://github.com/ashaheedq/araugment
Keywords: arabic,arabic nlp,nlp
Platform: UNKNOWN
Classifier: Development Status :: 5 - Production/Stable
Classifier: Natural Language :: Arabic
Classifier: Programming Language :: Python :: 3
Classifier: Programming Language :: Python :: 3.6
Classifier: Programming Language :: Python :: 3.7
Classifier: Programming Language :: Python :: 3.8
Classifier: Programming Language :: Python :: 3.9
Classifier: Programming Language :: Python :: 3 :: Only
Classifier: License :: OSI Approved :: MIT License
Classifier: Operating System :: OS Independent
Requires-Python: >=3.6
Requires-Dist: markovify
Requires-Dist: google-trans-new
Requires-Dist: requests
Provides-Extra: dev
Requires-Dist: check-manifest ; extra == 'dev'
